gng.py
graph.py
homology.py
neural_net.py
reeb.py
som.py
util.py
TopologicalLearningTechniques-0.2.1.dist-info/LICENSE.txt
TopologicalLearningTechniques-0.2.1.dist-info/METADATA
TopologicalLearningTechniques-0.2.1.dist-info/WHEEL
TopologicalLearningTechniques-0.2.1.dist-info/top_level.txt
TopologicalLearningTechniques-0.2.1.dist-info/RECORD
