Metadata-Version: 2.1
Name: TopologicalLearningTechniques
Version: 0.2.1
Summary: Package created for INF367AII at UiB
Home-page: UNKNOWN
License: UNKNOWN
Platform: UNKNOWN
Classifier: Programming Language :: Python :: 3.8
License-File: LICENSE.txt
Requires-Dist: numpy (~=1.21.3)
Requires-Dist: torch (~=1.11.0)
Requires-Dist: scikit-learn (~=1.0.2)
Requires-Dist: scipy (~=1.7.2)
